pakkenellik/__init__.py
pakkenellik/aws/__init__.py
pakkenellik/aws/s3.py
pakkenellik/config/__init__.py
pakkenellik/dataframe/__init__.py
pakkenellik/dataframe/clean_column_headers.py
pakkenellik/dataframe/datetime.py
pakkenellik/dataframe/numbers.py
pakkenellik/dataframe/regions.py
pakkenellik/datawrapper/__init__.py
pakkenellik/datawrapper/client.py
pakkenellik/google/sheets.py
pakkenellik/integration/__init__.py
pakkenellik/integration/client.py
pakkenellik/log/__init__.py
pakkenellik/log/ansi.py
pakkenellik/vegvesen/__init__.py
pakkenellik/vegvesen/visvegen.py
pakkenellik/viz/__init__.py
pakkenellik/viz/pyplot.py
pakkenellik-0.1.11.dist-info/WHEEL
pakkenellik-0.1.11.dist-info/METADATA
pakkenellik-0.1.11.dist-info/RECORD
