Metadata-Version: 2.1
Name: pakkenellik
Version: 0.1.11
Summary: Swiss army knife for Bord4's data anlysis
Author: Lasse Lambrechts
Author-email: lasse.lambrechts@bt.no
Requires-Python: >=3.10,<4.0
Classifier: Programming Language :: Python :: 3
Classifier: Programming Language :: Python :: 3.10
Classifier: Programming Language :: Python :: 3.11
Provides-Extra: gis
Provides-Extra: gspread
Provides-Extra: nvdb
Provides-Extra: s3
Provides-Extra: ssb
Requires-Dist: boto3 (>=1.26.39,<2.0.0) ; extra == "s3"
Requires-Dist: geopandas (>=0.12.2,<0.13.0) ; extra == "nvdb" or extra == "gis"
Requires-Dist: gspread (>=5.7.2,<6.0.0) ; extra == "gspread"
Requires-Dist: gspread-dataframe (>=3.3.0,<4.0.0) ; extra == "gspread"
Requires-Dist: gspread-formatting (>=1.1.2,<2.0.0) ; extra == "gspread"
Requires-Dist: pandas (>=2.1.2,<3.0.0)
Requires-Dist: plotly (>=5.11.0,<6.0.0)
Requires-Dist: pyjstat (>=2.3.0,<3.0.0) ; extra == "ssb"
Requires-Dist: python-dotenv (>=0.21.0,<0.22.0)
Requires-Dist: requests (>=2.28.1,<3.0.0)
